odoo/addons/shopfloor_reception_mobile/README.rst
odoo/addons/shopfloor_reception_mobile/__init__.py
odoo/addons/shopfloor_reception_mobile/__manifest__.py
odoo/addons/shopfloor_reception_mobile/i18n/it.po
odoo/addons/shopfloor_reception_mobile/i18n/shopfloor_reception_mobile.pot
odoo/addons/shopfloor_reception_mobile/readme/CONTRIBUTORS.rst
odoo/addons/shopfloor_reception_mobile/readme/DESCRIPTION.rst
odoo/addons/shopfloor_reception_mobile/static/description/icon.png
odoo/addons/shopfloor_reception_mobile/static/description/index.html
odoo/addons/shopfloor_reception_mobile/static/src/demo/demo.reception.js
odoo/addons/shopfloor_reception_mobile/static/src/scenario/reception.js
odoo/addons/shopfloor_reception_mobile/static/src/scenario/reception_states.js
odoo/addons/shopfloor_reception_mobile/templates/assets.xml
odoo14_addon_shopfloor_reception_mobile-14.0.0.9.0.dist-info/METADATA
odoo14_addon_shopfloor_reception_mobile-14.0.0.9.0.dist-info/WHEEL
odoo14_addon_shopfloor_reception_mobile-14.0.0.9.0.dist-info/top_level.txt
odoo14_addon_shopfloor_reception_mobile-14.0.0.9.0.dist-info/RECORD
